{
  "project_info": {
    "project_number": "928306766428",
    "project_id": "e-commerce-2eb4a",
    "storage_bucket": "e-commerce-2eb4a.appspot.com"
  },
  "client": [
    {
      "client_info": {
        "mobilesdk_app_id": "1:928306766428:android:e582979a1c03d811c7fc99",
        "android_client_info": {
          "package_name": "com.example.ecommmerce_app"
        }
      },
      "oauth_client": [
        {
          "client_id": "928306766428-75auscnkhceq2fdpm2ea4d9a1jsiuap2.apps.googleusercontent.com",
          "client_type": 3
        }
      ],
      "api_key": [
        {
          "current_key": "AIzaSyAgH8JTwu9_cF_q1WCySPSvGD7tATcT7is"
        }
      ],
      "services": {
        "appinvite_service": {
          "other_platform_oauth_client": [
            {
              "client_id": "928306766428-75auscnkhceq2fdpm2ea4d9a1jsiuap2.apps.googleusercontent.com",
              "client_type": 3
            }
          ]
        }
      }
    }
  ],
  "configuration_version": "1"
}